{
  "indexes": [
    {
      "collectionGroup": "jobs",
      "queryScope": "COLLECTION",
      "fields": [
        {
          "fieldPath": "status",
          "order": "ASCENDING"
        },
        {
          "fieldPath": "createdAt",
          "order": "DESCENDING"
        }
      ]
    },
    {
      "collectionGroup": "jobs",
      "queryScope": "COLLECTION",
      "fields": [
        {
          "fieldPath": "ownerId",
          "order": "ASCENDING"
        },
        {
          "fieldPath": "createdAt",
          "order": "DESCENDING"
        }
      ]
    },
    {
      "collectionGroup": "chatRooms",
      "queryScope": "COLLECTION",
      "fields": [
        {
          "fieldPath": "participants",
          "arrayConfig": "CONTAINS"
        },
        {
          "fieldPath": "lastMessageTime",
          "order": "DESCENDING"
        }
      ]
    },
    {
      "collectionGroup": "messages",
      "queryScope": "COLLECTION",
      "fields": [
        {
          "fieldPath": "chatRoomId",
          "order": "ASCENDING"
        },
        {
          "fieldPath": "timestamp",
          "order": "ASCENDING"
        }
      ]
    },
    {
      "collectionGroup": "notifications",
      "queryScope": "COLLECTION",
      "fields": [
        {
          "fieldPath": "userId",
          "order": "ASCENDING"
        },
        {
          "fieldPath": "timestamp",
          "order": "DESCENDING"
        }
      ]
    },
    {
      "collectionGroup": "jobApplications",
      "queryScope": "COLLECTION",
      "fields": [
        {
          "fieldPath": "userId",
          "order": "ASCENDING"
        },
        {
          "fieldPath": "appliedAt",
          "order": "DESCENDING"
        }
      ]
    }
  ],
  "fieldOverrides": []
}
